modelgauge/suts/huggingface_client.py
modelgauge/suts/huggingface_inference.py
modelgauge_huggingface-0.6.3.dist-info/METADATA
modelgauge_huggingface-0.6.3.dist-info/WHEEL
modelgauge_huggingface-0.6.3.dist-info/RECORD
