Metadata-Version: 2.1
Name: modelgauge-huggingface
Version: 0.6.3
Summary: 
Author: MLCommons AI Safety
Author-email: ai-safety-engineering@mlcommons.org
Requires-Python: >=3.10,<4.0
Classifier: Programming Language :: Python :: 3
Classifier: Programming Language :: Python :: 3.10
Classifier: Programming Language :: Python :: 3.11
Classifier: Programming Language :: Python :: 3.12
Requires-Dist: torch (>=2.1.2,<3.0.0)
Requires-Dist: transformers (>=4.38.1,<5.0.0)
